etsyv3/__init__.py
etsyv3/etsy_api.py
etsyv3/enums/__init__.py
etsyv3/enums/listing.py
etsyv3/enums/shipping_providers.py
etsyv3/models/__init__.py
etsyv3/models/file_request.py
etsyv3/models/listing_inventory.py
etsyv3/models/listing_property.py
etsyv3/models/listing_request.py
etsyv3/models/product.py
etsyv3/models/receipt_request.py
etsyv3/models/shop_request.py
etsyv3/util/__init__.py
etsyv3/util/todict.py
etsyv3/util/auth/__init__.py
etsyv3/util/auth/auth_helper.py
etsyv3-0.0.7.dist-info/LICENSE
etsyv3-0.0.7.dist-info/METADATA
etsyv3-0.0.7.dist-info/WHEEL
etsyv3-0.0.7.dist-info/top_level.txt
etsyv3-0.0.7.dist-info/RECORD
