Metadata-Version: 2.1
Name: etsyv3
Version: 0.0.7
Summary: A package to support the Etsy Open API v3
Author-email: anitabyte <anita@anitabyte.xyz>
License: GNU GENERAL PUBLIC LICENSE
Project-URL: Homepage, https://github.com/anitabyte/etsyv3
Project-URL: Bug Tracker, https://github.com/anitabyte/etsyv3/issues
Classifier: Programming Language :: Python :: 3
Classifier: License :: OSI Approved :: GNU General Public License v3 (GPLv3)
Classifier: Operating System :: OS Independent
Requires-Python: >=3.8
License-File: LICENSE
Requires-Dist: requests >=2.28.1
Requires-Dist: requests-oauthlib >=1.3.1
Provides-Extra: test
Requires-Dist: coverage >=5.0.3 ; extra == 'test'
Requires-Dist: pytest ; extra == 'test'
Requires-Dist: pytest-benchmark[histogram] >=3.2.1 ; extra == 'test'
Requires-Dist: black ; extra == 'test'
Requires-Dist: isort ; extra == 'test'
Requires-Dist: mypy ; extra == 'test'
Requires-Dist: types-requests ; extra == 'test'
Requires-Dist: build ; extra == 'test'
Requires-Dist: twine ; extra == 'test'
